napari_sediment/__init__.py
napari_sediment/_version.py
napari_sediment/napari.yaml
napari_sediment/_tests/__init__.py
napari_sediment/_tests/test_a_load_preprocess.py
napari_sediment/_tests/test_b_dim_reduc.py
napari_sediment/_tests/test_c_indices.py
napari_sediment/_tests/test_reader.py
napari_sediment/_tests/test_sediment_widget.py
napari_sediment/data/__init__.py
napari_sediment/data/data_contribution.py
napari_sediment/data/synthetic.py
napari_sediment/data_structures/imchannels.py
napari_sediment/data_structures/parameters.py
napari_sediment/data_structures/parameters_endmembers.py
napari_sediment/data_structures/parameters_plots.py
napari_sediment/data_structures/spectralindex.py
napari_sediment/deprecated/select_range.py
napari_sediment/utilities/_reader.py
napari_sediment/utilities/batch_preproc.py
napari_sediment/utilities/hyperanalysis.py
napari_sediment/utilities/images.py
napari_sediment/utilities/io.py
napari_sediment/utilities/morecolormaps.py
napari_sediment/utilities/sediproc.py
napari_sediment/utilities/spectralindex_compute.py
napari_sediment/utilities/spectralplot.py
napari_sediment/utilities/utils.py
napari_sediment/widget_utilities/channel_widget.py
napari_sediment/widget_utilities/classifier.py
napari_sediment/widget_utilities/folder_list_widget.py
napari_sediment/widget_utilities/rgb_widget.py
napari_sediment/widget_utilities/spectralplotter.py
napari_sediment/widgets/batch_indices.py
napari_sediment/widgets/batch_preproc_widget.py
napari_sediment/widgets/concatenation_widget.py
napari_sediment/widgets/convert_widget.py
napari_sediment/widgets/hyperanalysis_widget.py
napari_sediment/widgets/sediment_widget.py
napari_sediment/widgets/spectral_indices_widget.py
napari_sediment-0.4.0.dist-info/LICENSE
napari_sediment-0.4.0.dist-info/METADATA
napari_sediment-0.4.0.dist-info/WHEEL
napari_sediment-0.4.0.dist-info/entry_points.txt
napari_sediment-0.4.0.dist-info/top_level.txt
napari_sediment-0.4.0.dist-info/RECORD
