Metadata-Version: 2.2
Name: napari-sediment
Version: 0.4.0
Summary: A plugin to process hyperspectral images of sediments
Home-page: https://github.com/guiwitz/napari-sediment
Author: Guillaume Witz
Author-email: guillaume.witz@unibe.ch
License: BSD-3-Clause
Project-URL: Bug Tracker, https://github.com/guiwitz/napari-sediment/issues
Project-URL: Documentation, https://github.com/guiwitz/napari-sediment#README.md
Project-URL: Source Code, https://github.com/guiwitz/napari-sediment
Project-URL: User Support, https://github.com/guiwitz/napari-sediment/issues
Classifier: Development Status :: 2 - Pre-Alpha
Classifier: Framework :: napari
Classifier: Intended Audience :: Developers
Classifier: License :: OSI Approved :: BSD License
Classifier: Operating System :: OS Independent
Classifier: Programming Language :: Python
Classifier: Programming Language :: Python :: 3
Classifier: Programming Language :: Python :: 3 :: Only
Classifier: Programming Language :: Python :: 3.9
Classifier: Programming Language :: Python :: 3.10
Classifier: Programming Language :: Python :: 3.11
Classifier: Topic :: Scientific/Engineering :: Image Processing
Requires-Python: >=3.9
License-File: LICENSE
Requires-Dist: numpy<2
Requires-Dist: zarr<3
Requires-Dist: magicgui
Requires-Dist: qtpy
Requires-Dist: napari-guitils
Requires-Dist: napari-convpaint>=0.6.0
Requires-Dist: superqt
Requires-Dist: natsort
Requires-Dist: spectral
Requires-Dist: matplotlib
Requires-Dist: scikit-image
Requires-Dist: scikit-learn
Requires-Dist: PyYAML
Requires-Dist: microfilm
Requires-Dist: dask
Requires-Dist: distributed
Requires-Dist: tqdm
Requires-Dist: cmap
Requires-Dist: colour-science
Provides-Extra: testing
Requires-Dist: tox; extra == "testing"
Requires-Dist: pytest; extra == "testing"
Requires-Dist: pytest-cov; extra == "testing"
Requires-Dist: pytest-qt; extra == "testing"
Requires-Dist: napari; extra == "testing"
Requires-Dist: pyqt5; extra == "testing"
Provides-Extra: classifier
Requires-Dist: torch; extra == "classifier"
Requires-Dist: torchvision; extra == "classifier"
